dimfred/__init__.py
dimfred/config.py
dimfred/fastapi_utils.py
dimfred/loop.py
dimfred/pipe.py
dimfred/psutil_ext.py
dimfred/stopwatch.py
dimfred/worker.py
dimfred-0.18.0.dist-info/WHEEL
dimfred-0.18.0.dist-info/METADATA
dimfred-0.18.0.dist-info/RECORD
