Metadata-Version: 2.1
Name: dimfred
Version: 0.18.0
Summary: Tools and abbrevations I use often.
License: MIT
Author: Dmitrij Vinokour
Author-email: dimfred.1337@web.de
Requires-Python: >=3.7,<4.0
Classifier: License :: OSI Approved :: MIT License
Classifier: Programming Language :: Python :: 3
Classifier: Programming Language :: Python :: 3.10
Classifier: Programming Language :: Python :: 3.7
Classifier: Programming Language :: Python :: 3.8
Classifier: Programming Language :: Python :: 3.9
Requires-Dist: PyYAML (>=6.0,<7.0)
Requires-Dist: click (<8.1.0)
Requires-Dist: easydict (>=1.9,<2.0)
Requires-Dist: jsoncomment (>=0.4.2,<0.5.0)
Requires-Dist: pluck (>=0.2,<0.3)
Requires-Dist: prettyprint (>=0.1.5,<0.2.0)
Requires-Dist: psutil (>=5.9.0,<6.0.0)
Requires-Dist: shutils (>=0.1.0,<0.2.0)
Requires-Dist: tabulate (>=0.8.9,<0.9.0)
Requires-Dist: urlpath (>=1.2.0,<2.0.0)
